fractal_roles/__init__.py
fractal_roles/exceptions.py
fractal_roles/models.py
fractal_roles/py.typed
fractal_roles/services.py
fractal_roles-1.0.7.dist-info/LICENSE
fractal_roles-1.0.7.dist-info/WHEEL
fractal_roles-1.0.7.dist-info/METADATA
fractal_roles-1.0.7.dist-info/RECORD
