Metadata-Version: 2.1
Name: fractal-roles
Version: 1.0.7
Summary: Fractal Roles provides a flexible way to define fine-grained roles & permissions for users of your Python applications.
Home-page: https://github.com/douwevandermeij/fractal-roles
Author: Douwe van der Meij
Author-email: douwe@karibu-online.nl
Requires-Python: >=3.8
Classifier: Development Status :: 3 - Alpha
Classifier: Environment :: Web Environment
Classifier: Intended Audience :: Developers
Classifier: License :: OSI Approved :: MIT License
Classifier: Operating System :: OS Independent
Classifier: Programming Language :: Python :: 3
Classifier: Programming Language :: Python
Requires-Dist: fractal_specifications
Requires-Dist: black ; extra == "test"
Requires-Dist: flake8 ; extra == "test"
Requires-Dist: isort ; extra == "test"
Provides-Extra: test
